dbops_manager/__init__.py
dbops_manager/config_loader.py
dbops_manager/exceptions.py
dbops_manager/postgres_ops.py
dbops_manager-0.1.8.dist-info/licenses/LICENSE
dbops_manager-0.1.8.dist-info/METADATA
dbops_manager-0.1.8.dist-info/WHEEL
dbops_manager-0.1.8.dist-info/top_level.txt
dbops_manager-0.1.8.dist-info/RECORD
